md2notion/__init__.py
md2notion/core.py
md2notionpage/__init__.py
md2notionpage/cli.py
md2notionpage/core.py
md2notionpage-0.1.5.dist-info/LICENSE
md2notionpage-0.1.5.dist-info/METADATA
md2notionpage-0.1.5.dist-info/WHEEL
md2notionpage-0.1.5.dist-info/entry_points.txt
md2notionpage-0.1.5.dist-info/top_level.txt
md2notionpage-0.1.5.dist-info/RECORD
