Metadata-Version: 2.1
Name: md2notionpage
Version: 0.1.5
Summary: A package to convert Markdown text to Notion data structure and publish a new page under the parent page
Author: Marko T. Manninen
Author-email: elonmedia@gmail.com
License-File: LICENSE
Requires-Dist: notion-client
